cli_changelog_md/__init__.py
cli_changelog_md/cfg.py
cli_changelog_md/exception.py
cli_changelog_md/git.py
cli_changelog_md-2.9.2.data/scripts/changelog
cli_changelog_md-2.9.2.dist-info/METADATA
cli_changelog_md-2.9.2.dist-info/WHEEL
cli_changelog_md-2.9.2.dist-info/top_level.txt
cli_changelog_md-2.9.2.dist-info/RECORD
